octodns_gcore/__init__.py
octodns_gcore-1.0.0.dist-info/licenses/LICENSE
octodns_gcore-1.0.0.dist-info/METADATA
octodns_gcore-1.0.0.dist-info/WHEEL
octodns_gcore-1.0.0.dist-info/top_level.txt
octodns_gcore-1.0.0.dist-info/RECORD
