Metadata-Version: 2.4
Name: octodns-gcore
Version: 1.0.0
Summary:  Gcore DNS v2 API provider for octoDNS
Home-page: https://github.com/octodns/octodns-gcore
Author: Ross McFarland
Author-email: rwmcfa1@gmail.com
License: MIT
Requires-Python: >=3.9
License-File: LICENSE
Requires-Dist: octodns>=1.5.0
Requires-Dist: requests>=2.27.0
Provides-Extra: dev
Requires-Dist: pytest; extra == "dev"
Requires-Dist: pytest-cov; extra == "dev"
Requires-Dist: pytest-network; extra == "dev"
Requires-Dist: requests_mock; extra == "dev"
Requires-Dist: black<25.0.0,>=24.3.0; extra == "dev"
Requires-Dist: build>=0.7.0; extra == "dev"
Requires-Dist: isort>=5.11.5; extra == "dev"
Requires-Dist: pyflakes>=2.2.0; extra == "dev"
Requires-Dist: readme_renderer[md]>=26.0; extra == "dev"
Requires-Dist: twine>=3.4.2; extra == "dev"
Provides-Extra: test
Requires-Dist: pytest; extra == "test"
Requires-Dist: pytest-cov; extra == "test"
Requires-Dist: pytest-network; extra == "test"
Requires-Dist: requests_mock; extra == "test"
Dynamic: author
Dynamic: author-email
Dynamic: description
Dynamic: description-content-type
Dynamic: home-page
Dynamic: license
Dynamic: license-file
Dynamic: provides-extra
Dynamic: requires-dist
Dynamic: requires-python
Dynamic: summary
